udpnecho/__init__.py
udpnecho/__main__.py
udpnecho/pinyin2hanzi/__init__.py
udpnecho/pinyin2hanzi/dag.py
udpnecho/pinyin2hanzi/implement.py
udpnecho/pinyin2hanzi/interface.py
udpnecho/pinyin2hanzi/priorityset.py
udpnecho/pinyin2hanzi/util.py
udpnecho/pinyin2hanzi/viterbi.py
udpnecho/pinyin2hanzi/data/dag_char.json
udpnecho/pinyin2hanzi/data/dag_phrase.json
udpnecho/pinyin2hanzi/data/hmm_emission.json
udpnecho/pinyin2hanzi/data/hmm_py2hz.json
udpnecho/pinyin2hanzi/data/hmm_start.json
udpnecho/pinyin2hanzi/data/hmm_transition.json
udpnecho-0.1.1.dist-info/LICENSE
udpnecho-0.1.1.dist-info/METADATA
udpnecho-0.1.1.dist-info/WHEEL
udpnecho-0.1.1.dist-info/entry_points.txt
udpnecho-0.1.1.dist-info/top_level.txt
udpnecho-0.1.1.dist-info/RECORD
