Metadata-Version: 2.1
Name: udpnecho
Version: 0.1.1
Summary: shuangpin tools
Home-page: https://github.com/vang1ong7ang/udpnecho
Author: vang1ong7ang
Author-email: vang1ong7ang@outlook.com
License: MIT License
Project-URL: Bug Tracker, https://github.com/vang1ong7ang/udpnecho/issues
Platform: UNKNOWN
Classifier: Programming Language :: Python :: 3
Classifier: License :: OSI Approved :: MIT License
Classifier: Operating System :: OS Independent
Requires-Python: >=3.6
License-File: LICENSE
